reusable_lib/__init__.py
reusable_lib/reusable_analysis.py
reusable_lib/reusable_argparse.py
reusable_lib/reusable_db.py
reusable_lib/reusable_file.py
reusable_lib/reusable_hash.py
reusable_lib/reusable_json.py
reusable_lib/reusable_ldd.py
reusable_lib/reusable_nav.py
reusable_lib/reusable_pickle.py
reusable_lib/reusable_stat.py
reusable_lib/reusable_strings.py
reusable_lib/reusable_summary.py
reusable_lib/reusable_utils.py
reusable_lib/reusable_vt.py
reusable_lib-0.3.3.dist-info/METADATA
reusable_lib-0.3.3.dist-info/WHEEL
reusable_lib-0.3.3.dist-info/licenses/LICENSE
reusable_lib-0.3.3.dist-info/RECORD
