Metadata-Version: 2.3
Name: reusable_lib
Version: 0.3.3
Summary: A bunch of reusable things
Project-URL: Homepage, https://github.com/syssec-lib/reusable_lib
Project-URL: Issues, https://github.com/syssec-lib/reusable_lib/issues
Author-email: JJR <jhrhee@gmail.com>
License: MIT License
License-File: LICENSE
Classifier: License :: OSI Approved :: MIT License
Classifier: Operating System :: OS Independent
Classifier: Programming Language :: Python :: 3
Requires-Python: >=3.8
Requires-Dist: psycopg2
Requires-Dist: py-tlsh
Requires-Dist: pylddwrap
Requires-Dist: pylint
Requires-Dist: python-magic
Requires-Dist: sdhash
Requires-Dist: telfhash
Requires-Dist: vt
Requires-Dist: yapf
